archil/__init__.py
archil/_sync.py
archil/client.py
archil/containers.py
archil/disks.py
archil/environment.py
archil/exceptions.py
archil-0.1.4.dist-info/METADATA
archil-0.1.4.dist-info/WHEEL
archil-0.1.4.dist-info/RECORD
